biginsight/__init__.py
biginsight/core.py
trackus-0.0.26.dist-info/LICENSE
trackus-0.0.26.dist-info/METADATA
trackus-0.0.26.dist-info/WHEEL
trackus-0.0.26.dist-info/top_level.txt
trackus-0.0.26.dist-info/RECORD
