Metadata-Version: 2.1
Name: trackus
Version: 0.0.26
Summary: Track all user's action on a mobile app and website
Author: Geottuse
Author-email: admin@geottuse.com
Classifier: Programming Language :: Python :: 3
Classifier: License :: OSI Approved :: MIT License
Classifier: Operating System :: OS Independent
Requires-Python: >=3.9
License-File: LICENSE
